Workbook

Sheet Summary
A1: Drift — Changelog
A2: Every feature, fix and change shipped. 2026-07-07 – 2026-10-12.
A4: Total changes | B4: =COUNTA(Changes!E2:E158)
A6: By type | D6: By area | G6: By release
A7: Type | B7: Count | D7: Area | E7: Count | G7: Release | H7: Count
A8: Feature | B8: =COUNTIF(Changes!$C$2:$C$158,A8) | D8: AI Check | E8: =COUNTIF(Changes!$D$2:$D$158,D8) | G8: 1.1.2 | H8: =COUNTIF(Changes!$G$2:$G$158,G8)
A9: Bug Fix | B9: =COUNTIF(Changes!$C$2:$C$158,A9) | D9: Action Plan | E9: =COUNTIF(Changes!$D$2:$D$158,D9) | G9: 1.1.3 | H9: =COUNTIF(Changes!$G$2:$G$158,G9)
A10: UI | B10: =COUNTIF(Changes!$C$2:$C$158,A10) | D10: Add Task | E10: =COUNTIF(Changes!$D$2:$D$158,D10) | G10: 1.1.4 | H10: =COUNTIF(Changes!$G$2:$G$158,G10)
A11: Infra | B11: =COUNTIF(Changes!$C$2:$C$158,A11) | D11: Analytics | E11: =COUNTIF(Changes!$D$2:$D$158,D11) | G11: 1.1.6 | H11: =COUNTIF(Changes!$G$2:$G$158,G11)
A12: Security | B12: =COUNTIF(Changes!$C$2:$C$158,A12) | D12: Auth | E12: =COUNTIF(Changes!$D$2:$D$158,D12) | G12: 1.1.7 | H12: =COUNTIF(Changes!$G$2:$G$158,G12)
A13: Chore | B13: =COUNTIF(Changes!$C$2:$C$158,A13) | D13: Auth / Sync | E13: =COUNTIF(Changes!$D$2:$D$158,D13) | G13: 1.1.8 | H13: =COUNTIF(Changes!$G$2:$G$158,G13)
A14: Docs | B14: =COUNTIF(Changes!$C$2:$C$158,A14) | D14: Backend | E14: =COUNTIF(Changes!$D$2:$D$158,D14) | G14: 1.2.0 | H14: =COUNTIF(Changes!$G$2:$G$158,G14)
D15: Billing | E15: =COUNTIF(Changes!$D$2:$D$158,D15) | G15: Unreleased | H15: =COUNTIF(Changes!$G$2:$G$158,G15)
D16: CI/CD | E16: =COUNTIF(Changes!$D$2:$D$158,D16)
D17: Calendar | E17: =COUNTIF(Changes!$D$2:$D$158,D17)
D18: Challenges | E18: =COUNTIF(Changes!$D$2:$D$158,D18)
D19: Codes | E19: =COUNTIF(Changes!$D$2:$D$158,D19)
D20: Cohort codes | E20: =COUNTIF(Changes!$D$2:$D$158,D20)
D21: Dependencies | E21: =COUNTIF(Changes!$D$2:$D$158,D21)
D22: Dev | E22: =COUNTIF(Changes!$D$2:$D$158,D22)
D23: Discoverability | E23: =COUNTIF(Changes!$D$2:$D$158,D23)
D24: Drift In | E24: =COUNTIF(Changes!$D$2:$D$158,D24)
D25: Entitlement | E25: =COUNTIF(Changes!$D$2:$D$158,D25)
D26: Family | E26: =COUNTIF(Changes!$D$2:$D$158,D26)
D27: Force update | E27: =COUNTIF(Changes!$D$2:$D$158,D27)
... D53: Website | E53: =COUNTIF(Changes!$D$2:$D$158,D53)
A56: Notes
A57: • 1.1.8 is the last version submitted to the App Store. Everything marked Unreleased is on main but not shipped.
A58: • "Needs" says what a change requires beyond a normal JS reload: a native rebuild, an edge-function deploy, or SQL run in Supabase.
A59: • Native-build items are currently blocked on Apple Developer account access, so they are not device-tested.
A60: • Counts on this sheet are formulas over the Changes tab — they update if you edit, add or delete rows there.

Sheet Changes
A1: Date | B1: Commit | C1: Type | D1: Area | E1: Change | F1: Details | G1: Release | H1: Needs
A2: 2026-07-07 | B2: 3cbe56d | C2: Feature | D2: Onboarding | E2: Onboarding moved to after signup and shortened | F2: Pre-signup questionnaire was driving people away; profiling questions dropped entirely. | G2: 1.1.2 | H2: —
A3: 2026-07-07 | B3: 3cbe56d | C3: Feature | D3: Screen Time | E3: 30 minutes of screen time pre-added for new accounts | F3: Welcome bonus so a new user isn't locked out before earning anything. | G3: 1.1.2 | H3: —
A4: 2026-07-07 | B4: 3cbe56d | C4: Bug Fix | D4: Auth / Sync | E4: Tasks and screen time disappeared after sign out then sign in | F4: In-app sign-in never called fetchTasks (only cold boot did). Added hydrateTasksFromServer on every sign-in. | G4: 1.1.2 | H4: —
A5: 2026-07-07 | B5: 3cbe56d | C5: Infra | D5: Scaling | E5: Scale review for 100 / 1,000 / 10,000+ users | F5: Bounded task fetches (365-day window, 1,000 rows), caching and rate-limit guards to cut Supabase egress. | G5: 1.1.2 | H5: —
A6: 2026-07-07 | B6: 3cbe56d | C6: Feature | D6: Auth | E6: Sign in with Apple | F6: Added to onboarding (later hidden until Apple config was done). | G6: 1.1.2 | H6: —
A7: 2026-07-07 | B7: e167393 | C7: Feature | D7: Billing | E7: All payments removed — every feature free | F7: Paywall, upgrade links and purchase UI removed; RevenueCat code kept dormant behind a single flag for later re-enable. | G7: 1.1.2 | H7: —
A8: 2026-07-07 | B8: 7bc033f | C8: Chore | D8: Auth | E8: Phone (SMS OTP) sign-in removed | F8: Reversed after finding SMS auth costs money per message. | G8: 1.1.2 | H8: —
A9: 2026-07-10 | B9: d000ebb | C9: Bug Fix | D9: Auth | E9: Cold-start sign-outs from AES key generation race | F9: Encryption key was generated concurrently on launch; serialized it so cached sessions survive a cold start. | G9: 1.1.2 | H9: —
A10: 2026-07-10 | B10: ee8f346 | C10: Feature | D10: Tasks | E10: Async task valuation — no more waiting on the AI spinner | F10: Task appears instantly with provisional credits; the real AI value patches in when the server answers. | G10: 1.1.2 | H10: —
A11: 2026-07-10 | B11: ee8f346 | C11: Feature | D11: Tasks | E11: Non-productive credit cap | F11: Leisure/maintenance tasks capped at 1/5 of duration, enforced server-side so a stale client can't bypass it. | G11: 1.1.2 | H11: —
A12: 2026-07-12 | B12: c13b2b6 | C12: Bug Fix | D12: Auth | E12: Google users signed out on every cold start | F12: Email-verification check ran for OAuth users, whose cached session lacks email_confirmed_at. OAuth users are provider-verified — check skipped. | G12: 1.1.2 | H12: —
... A45: 2026-07-17 | B45: 8e29898 | C45: UI | D45: Add Task | E45: Add Task page rebuilt with the input at the bottom | F45: Thumb-reachable bottom dock for the task name. | G45: 1.1.6 | H45: —
A46: 2026-07-17 | B46: 8e29898 | C46: UI | D46: Drift In | E46: Info circle added, bottom tagline removed, input moved to bottom dock | G46: 1.1.6 | H46: —
A47: 2026-07-17 | B47: 8e29898 | C47: UI | D47: Theme | E47: Aurora backdrop extended to Stats and Grove | G47: 1.1.6 | H47: —
A48: 2026-07-17 | B48: 8e29898 | C48: Infra | D48: CI/CD | E48: GitHub Actions workflow for EAS builds | F48: Manual trigger with platform + profile inputs. Blocked on Apple Developer account credentials. | G48: 1.1.6 | H48: —
A49: 2026-07-18 | B49: da10977 | C49: Bug Fix | D49: Release | E49: Forced updates never actually fired | F49: Version lookup used app.json's bundle id (com.drift.app) but the signed app is com.sanghani.drift, so iTunes returned nothing. Corrected both. | G49: 1.1.6 | H49: —
A50: 2026-07-19 | B50: 0f42415 | C50: Bug Fix | D50: Notifications | E50: Out-of-time notification spam | F50: Two code paths fired it, and both re-fired on every app reopen. Now latched with persisted flags: one notification per depletion, re-armed when the balance goes positive. | G50: 1.1.6 | H50: —
A51: 2026-07-19 | B51: 0f42415 | C51: Feature | D51: Tasks | E51: Location-based task suggestions | F51: Save your own places (gym, office); arriving fires a notification that opens a prefilled, editable confirm sheet. Coordinates never leave the device — no Places API. | G51: 1.1.6 | H51: Native build
A52: 2026-07-19 | B52: 0f42415 | C52: Feature | D52: Tasks | E52: Optional calendar sync | F52: Read-only import of today's events as tasks, deduped by event id so re-syncing never duplicates. | G52: 1.1.6 | H52: Native build
A53: 2026-07-19 | B53: f41ba2c | C53: Feature | D53: Tasks | E53: AI now classifies the task category | F53: Category picker removed entirely. Classified server-side in the same round trip that values the task, against a fixed whitelist validated on both ends. | G53: 1.1.6 | H53: Edge deploy
A54: 2026-07-19 | B54: f41ba2c | C54: Feature | D54: Calendar | E54: Google Calendar preferred by default | F54: Google-backed calendars detected, badged, sorted first and preselected; device calendars remain switchable. | G54: 1.1.6 | H54: Native build
A55: 2026-07-19 | B55: f41ba2c | C55: UI | D55: Add Task | E55: AI explanation collapsed into a tappable mark | F55: Was a permanent block of text; now one icon that reveals it on tap. | G55: 1.1.6 | H55: —
A56: 2026-07-19 | B56: f41ba2c | C56: Feature | D56: Discoverability | E56: Automatic tasks surfaced in three quiet places | F56: Optional opt-in step at the end of onboarding, a one-line dismissible nudge on Today, and a single line in Add Task. All self-removing once acted on. | G56: 1.1.6 | H56: —
A57: 2026-07-19 | B57: d03609a | C57: UI | D57: Add Task | E57: Repeat picker collapsed into a disclosure row | F57: Five always-visible pills replaced by one row that expands into a list. | G57: 1.1.6 | H57: —
A58: 2026-07-19 | B58: 42112c1 | C58: UI | D58: Add Task | E58: Estimated earnings preview + quick length chips | F58: Fills the space the category picker left; 15m/30m/1h/2h chips snap to the slider's step. | G58: 1.1.6 | H58: —
A59: 2026-07-20 | B59: 1677732 | C59: Feature | D59: Navigation | E59: The Lab — new fourth tab for behaviour settings | F59: Holds blocked apps/hours, automatic tasks, recurring tasks and tour replay, moved out of Profile. Stats merged into The Grove to make room. | G59: 1.1.6 | H59: —
... A158: 2026-10-12 | B158: 90dc57e | C158: Feature | D158: Billing | E158: Loyalty pricing: monthly Pro drops 50¢ every 2 months, down to $2.99 | F158: $4.99 for months 0-1, then $4.49, $3.99, $3.49 and $2.99 from month 8, counted over an unbroken paid run (trial days excluded). Unsubscribing or lapsing resets it. Apple won't let an app change one subscriber's price, so each step is a promotional offer on com.drift.pro.month (loyalty_449/399/349 for 2 months, loyalty_299 for 12) that the subscriber confirms once; it starts at their next renewal. The webhook keeps profiles.sub_paid_since (guarded like the other subscription columns). Ships switched off: needs schema_v22 pushed, the webhook deployed, the four offers in App Store Connect, the subscription key in RevenueCat, then app_config.loyalty_pricing = 'true'. | G158: 1.2.0 | H158: SQL migration, Edge deploy, App Store Connect
